odoo/addons/stock_picking_auto_create_lot_qty/README.rst
odoo/addons/stock_picking_auto_create_lot_qty/__init__.py
odoo/addons/stock_picking_auto_create_lot_qty/__manifest__.py
odoo/addons/stock_picking_auto_create_lot_qty/i18n/stock_picking_auto_create_lot_qty.pot
odoo/addons/stock_picking_auto_create_lot_qty/models/__init__.py
odoo/addons/stock_picking_auto_create_lot_qty/models/product_template.py
odoo/addons/stock_picking_auto_create_lot_qty/models/res_company.py
odoo/addons/stock_picking_auto_create_lot_qty/models/res_config_settings.py
odoo/addons/stock_picking_auto_create_lot_qty/models/stock_lot.py
odoo/addons/stock_picking_auto_create_lot_qty/models/stock_picking.py
odoo/addons/stock_picking_auto_create_lot_qty/readme/CONFIGURE.rst
odoo/addons/stock_picking_auto_create_lot_qty/readme/CONTRIBUTORS.rst
odoo/addons/stock_picking_auto_create_lot_qty/readme/DESCRIPTION.rst
odoo/addons/stock_picking_auto_create_lot_qty/readme/USAGE.rst
odoo/addons/stock_picking_auto_create_lot_qty/static/description/icon.png
odoo/addons/stock_picking_auto_create_lot_qty/static/description/index.html
odoo/addons/stock_picking_auto_create_lot_qty/tests/__init__.py
odoo/addons/stock_picking_auto_create_lot_qty/tests/common.py
odoo/addons/stock_picking_auto_create_lot_qty/tests/test_stock_picking_auto_create_lot_qty.py
odoo/addons/stock_picking_auto_create_lot_qty/views/product_template_view.xml
odoo/addons/stock_picking_auto_create_lot_qty/views/res_config_settings_view.xml
odoo_addon_stock_picking_auto_create_lot_qty-16.0.1.0.0.2.dist-info/METADATA
odoo_addon_stock_picking_auto_create_lot_qty-16.0.1.0.0.2.dist-info/WHEEL
odoo_addon_stock_picking_auto_create_lot_qty-16.0.1.0.0.2.dist-info/top_level.txt
odoo_addon_stock_picking_auto_create_lot_qty-16.0.1.0.0.2.dist-info/RECORD
