Metadata-Version: 2.1
Name: odoo-addon-stock_picking_auto_create_lot_qty
Version: 16.0.1.0.0.2
Summary: Auto batch generation by quantity
Home-page: https://github.com/OCA/stock-logistics-workflow
Author: Ooops, Cetmix OÜ, Odoo Community Association (OCA)
Author-email: support@odoo-community.org
License: AGPL-3
Classifier: Programming Language :: Python
Classifier: Framework :: Odoo
Classifier: Framework :: Odoo :: 16.0
Classifier: License :: OSI Approved :: GNU Affero General Public License v3
Classifier: Development Status :: 5 - Production/Stable
Requires-Python: >=3.10
Requires-Dist: odoo-addon-stock-picking-auto-create-lot<16.1dev,>=16.0dev
Requires-Dist: odoo<16.1dev,>=16.0a
